{
    "backend": "django",
    "db_name": "",
    "db_pass": "",
    "db_type": "",
    "db_user": "",
    "dbms": "0",
    "description": "generated product",
    "design": "datta-able",
    "docker": "0",
    "err_code": 0,
    "frontend": "",
    "heroku": "0",
    "pattern": "mvc",
    "pro": "0",
    "task_id": "f57945d5-5f83-46de-b65d-39ad23070cf7",
    "task_info": "Upload Sources [0%] - 162 files",
    "task_output": "f57945d5-5f83-46de-b65d-39ad23070cf7.zip",
    "task_result": "SUCCESS",
    "task_state": "RUNNING",
    "task_ts_end": "2022-07-11-08-25-21",
    "task_ts_start": "2022-07-11-08-25-20"
}